odoo/addons/mrp_production_component_availability_search/README.rst
odoo/addons/mrp_production_component_availability_search/__init__.py
odoo/addons/mrp_production_component_availability_search/__manifest__.py
odoo/addons/mrp_production_component_availability_search/i18n/it.po
odoo/addons/mrp_production_component_availability_search/i18n/mrp_production_component_availability_search.pot
odoo/addons/mrp_production_component_availability_search/models/__init__.py
odoo/addons/mrp_production_component_availability_search/models/mrp_production.py
odoo/addons/mrp_production_component_availability_search/readme/CONTRIBUTORS.rst
odoo/addons/mrp_production_component_availability_search/readme/DESCRIPTION.rst
odoo/addons/mrp_production_component_availability_search/static/description/icon.png
odoo/addons/mrp_production_component_availability_search/static/description/index.html
odoo/addons/mrp_production_component_availability_search/tests/__init__.py
odoo/addons/mrp_production_component_availability_search/tests/test_search.py
odoo/addons/mrp_production_component_availability_search/views/mrp_production.xml
odoo_addon_mrp_production_component_availability_search-15.0.1.0.0.6.dist-info/METADATA
odoo_addon_mrp_production_component_availability_search-15.0.1.0.0.6.dist-info/WHEEL
odoo_addon_mrp_production_component_availability_search-15.0.1.0.0.6.dist-info/top_level.txt
odoo_addon_mrp_production_component_availability_search-15.0.1.0.0.6.dist-info/RECORD
